reflex_suneditor/__init__.py
reflex_suneditor/editor.py
reflex_suneditor-0.0.11.dist-info/METADATA
reflex_suneditor-0.0.11.dist-info/WHEEL
reflex_suneditor-0.0.11.dist-info/RECORD
