Metadata-Version: 2.1
Name: reflex-suneditor
Version: 0.0.11
Summary: Reflex suneditor
Author: Akshay Awate
Author-email: akshayawate2012@gmail.com
Requires-Python: >=3.7,<4.0
Classifier: Programming Language :: Python :: 3
Classifier: Programming Language :: Python :: 3.7
Classifier: Programming Language :: Python :: 3.8
Classifier: Programming Language :: Python :: 3.9
Classifier: Programming Language :: Python :: 3.10
Classifier: Programming Language :: Python :: 3.11
Classifier: Programming Language :: Python :: 3.12
Requires-Dist: reflex (==0.6.2)
